ipymuvue/__init__.py
ipymuvue/special.py
ipymuvue/version.py
ipymuvue/vue.py
ipymuvue/vue_widget.py
ipymuvue/labextension/package.json
ipymuvue/labextension/static/138.01408e93d52a52da893c.js
ipymuvue/labextension/static/138.3c655cfe79ebdf268d25.js
ipymuvue/labextension/static/138.4aaa6dfd96ca5ef895fc.js
ipymuvue/labextension/static/138.5996e5c40f819ae4a017.js
ipymuvue/labextension/static/138.70eb71e6f4ece6955f4e.js
ipymuvue/labextension/static/138.7754e404ae199afdfb03.js
ipymuvue/labextension/static/138.9aaf93b8742a72c60691.js
ipymuvue/labextension/static/138.9fd20bea98d05031217f.js
ipymuvue/labextension/static/138.abbd9450db2c25d2ccdd.js
ipymuvue/labextension/static/138.b036d6cee52bce70d57b.js
ipymuvue/labextension/static/138.b63173e32a0d09adbb2f.js
ipymuvue/labextension/static/138.e05060e92e5c5d540bd3.js
ipymuvue/labextension/static/518.0e4a0cd71c588494c03a.js
ipymuvue/labextension/static/518.3a4501ed547d88e52573.js
ipymuvue/labextension/static/518.4e2585a157097dec667b.js
ipymuvue/labextension/static/518.5401a9b9eb3f70524000.js
ipymuvue/labextension/static/518.549dea5f405c0dcddf09.js
ipymuvue/labextension/static/518.79d5f75a9b529f868e91.js
ipymuvue/labextension/static/518.7f7391abd8236191e360.js
ipymuvue/labextension/static/518.8a2fbc6fcdd9984a99fa.js
ipymuvue/labextension/static/518.8ffbaac22e129b82fd65.js
ipymuvue/labextension/static/518.c14bdc50295ad79bda9c.js
ipymuvue/labextension/static/518.d2397061dac43c7be3ff.js
ipymuvue/labextension/static/520.6729ee70d0e375c09de2.js
ipymuvue/labextension/static/520.6729ee70d0e375c09de2.js.LICENSE.txt
ipymuvue/labextension/static/549.2e2820657b3357b7cf7d.js
ipymuvue/labextension/static/549.2e2820657b3357b7cf7d.js.LICENSE.txt
ipymuvue/labextension/static/549.9f62ada177f281047fb0.js
ipymuvue/labextension/static/549.9f62ada177f281047fb0.js.LICENSE.txt
ipymuvue/labextension/static/908.0ff577652419398ccb57.js
ipymuvue/labextension/static/908.32e35f88acfa50bc73fe.js
ipymuvue/labextension/static/908.41e8ad86e4bd31405e7f.js
ipymuvue-0.6.0.dist-info/COPYING
ipymuvue-0.6.0.dist-info/METADATA
ipymuvue-0.6.0.dist-info/WHEEL
ipymuvue-0.6.0.dist-info/top_level.txt
ipymuvue-0.6.0.dist-info/RECORD
