Metadata-Version: 2.1
Name: ipymuvue
Version: 0.6.0
Summary: Reactive Jupyter Widgets
Home-page: https://github.com/flatsurf/ipymuvue
Author: Julian Rüth
Author-email: julian.rueth@fsfe.org
Keywords: ipython,jupyter,widgets
Classifier: Development Status :: 4 - Beta
Classifier: Framework :: IPython
Classifier: License :: OSI Approved :: MIT License
Classifier: Intended Audience :: Developers
Classifier: Programming Language :: Python :: 3.6
Classifier: Programming Language :: Python :: 3.7
Classifier: Programming Language :: Python :: 3.8
Classifier: Programming Language :: Python :: 3.9
License-File: COPYING
Requires-Dist: ipywidgets <9,>=7
Requires-Dist: jupyter-ui-poll <0.3,>=0.2.1
